utt/__init__.py
utt/__main__.py
utt/__version__.py
utt/api/__init__.py
utt/api/_v1/__init__.py
utt/api/_v1/_private.py
utt/command.py
utt/components/__init__.py
utt/components/activities.py
utt/components/add_entry.py
utt/components/commands.py
utt/components/config.py
utt/components/config_dirname.py
utt/components/config_filename.py
utt/components/data_dirname.py
utt/components/data_filename.py
utt/components/default_config.py
utt/components/entries.py
utt/components/entry_lines.py
utt/components/entry_parser.py
utt/components/now.py
utt/components/output.py
utt/components/parse_args.py
utt/components/report_args.py
utt/components/report_model/__init__.py
utt/components/report_model/model.py
utt/components/report_view.py
utt/constants.py
utt/data_structures/__init__.py
utt/data_structures/activity.py
utt/data_structures/entry.py
utt/data_structures/name.py
utt/exceptions.py
utt/plugins/0_add.py
utt/plugins/0_config.py
utt/plugins/0_default_report_view.py
utt/plugins/0_edit.py
utt/plugins/0_hello.py
utt/plugins/0_report.py
utt/plugins/0_stretch.py
utt/plugins/__init__.py
utt/report/__init__.py
utt/report/activities/__init__.py
utt/report/activities/model.py
utt/report/activities/view.py
utt/report/common.py
utt/report/csv_view.py
utt/report/details/__init__.py
utt/report/details/model.py
utt/report/details/view.py
utt/report/formatter.py
utt/report/per_day/__init__.py
utt/report/per_day/model.py
utt/report/per_day/view.py
utt/report/projects/__init__.py
utt/report/projects/model.py
utt/report/projects/view.py
utt/report/summary/__init__.py
utt/report/summary/model.py
utt/report/summary/view.py
utt/version.txt
utt-1.32.dist-info/METADATA
utt-1.32.dist-info/WHEEL
utt-1.32.dist-info/entry_points.txt
utt-1.32.dist-info/licenses/LICENSE
utt-1.32.dist-info/RECORD
