Metadata-Version: 2.4
Name: utt
Version: 1.32
Summary: A simple command-line time tracker
License: GPL-3.0-only
License-File: LICENSE
Author: Mathieu Larose
Author-email: mathieu@mathieularose.com
Maintainer: Mathieu Larose
Maintainer-email: mathieu@mathieularose.com
Requires-Python: >=3.10,<4.0
Classifier: License :: OSI Approved :: GNU General Public License v3 (GPLv3)
Classifier: Programming Language :: Python :: 3
Classifier: Programming Language :: Python :: 3.10
Classifier: Programming Language :: Python :: 3.11
Classifier: Programming Language :: Python :: 3.12
Classifier: Programming Language :: Python :: 3.13
Classifier: Programming Language :: Python :: 3.14
Requires-Dist: argcomplete (>=3.2.1,<4.0.0)
Requires-Dist: cargo (>=0.3,<0.4)
Project-URL: Homepage, https://github.com/larose/utt
